Workbook

Sheet README
A1: Day 14 - FINAL EXCEL PROJECT
A3: Project: Sales Analytics + Employee Analytics
A5: Complete topics included:
A6: 1. Excel Basics & Formatting
A7: 2. Excel Tables
A8: 3. Basic Functions
A9: 4. IF / AND / OR / IFERROR
A10: 5. SUMIF / SUMIFS / COUNTIF / COUNTIFS / AVERAGEIF
A11: 6. XLOOKUP / VLOOKUP / INDEX-MATCH
A12: 7. LEFT / RIGHT / MID / LEN / TRIM / UPPER / LOWER / PROPER
A13: 8. CONCAT / TEXTJOIN / SUBSTITUTE / FIND / SEARCH / REPLACE
A14: 9. YEAR / MONTH / DAY / WEEKDAY / WEEKNUM / EOMONTH / TODAY
... A17: 12. Dashboard

Sheet Raw_Data
A3: Order_ID | B3: Date | C3: Region | D3: Category | E3: Product | F3: Salesperson | G3: Qty | H3: Price | I3: Discount | J3: Status | K3: Gross Sales | L3: Discount Amount | M3: Net Sales | N3: Profit | O3: Month | P3: Year | Q3: Day
A4: O001 | B4: 45690 | C4: South | D4: Electronics | E4: Laptop | F4: Riya | G4: 2 | H4: 55000 | I4: 0.02 | J4: Completed | K4: =G4*H4 | L4: =K4*I4 | M4: =K4-L4 | N4: =M4*IF(D4="Electronics",0.15,IF(D4="Furniture",0.20,0.25)) | O4: =TEXT(B4,"mmm") | P4: =YEAR(B4) | Q4: =TEXT(B4,"dddd")
A5: O002 | B5: 45719 | C5: East | D5: Electronics | E5: Monitor | F5: Rahul | G5: 3 | H5: 18000 | I5: 0.05 | J5: Pending | K5: =G5*H5 | L5: =K5*I5 | M5: =K5-L5 | N5: =M5*IF(D5="Electronics",0.15,IF(D5="Furniture",0.20,0.25)) | O5: =TEXT(B5,"mmm") | P5: =YEAR(B5) | Q5: =TEXT(B5,"dddd")
A6: O003 | B6: 45751 | C6: West | D6: Accessories | E6: Mouse | F6: Neha | G6: 4 | H6: 900 | I6: 0.08 | J6: Cancelled | K6: =G6*H6 | L6: =K6*I6 | M6: =K6-L6 | N6: =M6*IF(D6="Electronics",0.15,IF(D6="Furniture",0.20,0.25)) | O6: =TEXT(B6,"mmm") | P6: =YEAR(B6) | Q6: =TEXT(B6,"dddd")
A7: O004 | B7: 45782 | C7: North | D7: Furniture | E7: Chair | F7: Kabir | G7: 5 | H7: 8500 | I7: 0.1 | J7: Completed | K7: =G7*H7 | L7: =K7*I7 | M7: =K7-L7 | N7: =M7*IF(D7="Electronics",0.15,IF(D7="Furniture",0.20,0.25)) | O7: =TEXT(B7,"mmm") | P7: =YEAR(B7) | Q7: =TEXT(B7,"dddd")
A8: O005 | B8: 45814 | C8: South | D8: Furniture | E8: Desk | F8: Sana | G8: 6 | H8: 12000 | I8: 0 | J8: Completed | K8: =G8*H8 | L8: =K8*I8 | M8: =K8-L8 | N8: =M8*IF(D8="Electronics",0.15,IF(D8="Furniture",0.20,0.25)) | O8: =TEXT(B8,"mmm") | P8: =YEAR(B8) | Q8: =TEXT(B8,"dddd")
A9: O006 | B9: 45845 | C9: East | D9: Accessories | E9: Keyboard | F9: Ishaan | G9: 7 | H9: 1800 | I9: 0.02 | J9: Pending | K9: =G9*H9 | L9: =K9*I9 | M9: =K9-L9 | N9: =M9*IF(D9="Electronics",0.15,IF(D9="Furniture",0.20,0.25)) | O9: =TEXT(B9,"mmm") | P9: =YEAR(B9) | Q9: =TEXT(B9,"dddd")
A10: O007 | B10: 45877 | C10: West | D10: Electronics | E10: Laptop | F10: Meera | G10: 8 | H10: 55000 | I10: 0.05 | J10: Cancelled | K10: =G10*H10 | L10: =K10*I10 | M10: =K10-L10 | N10: =M10*IF(D10="Electronics",0.15,IF(D10="Furniture",0.20,0.25)) | O10: =TEXT(B10,"mmm") | P10: =YEAR(B10) | Q10: =TEXT(B10,"dddd")
A11: O008 | B11: 45909 | C11: North | D11: Electronics | E11: Monitor | F11: Aarav | G11: 1 | H11: 18000 | I11: 0.08 | J11: Completed | K11: =G11*H11 | L11: =K11*I11 | M11: =K11-L11 | N11: =M11*IF(D11="Electronics",0.15,IF(D11="Furniture",0.20,0.25)) | O11: =TEXT(B11,"mmm") | P11: =YEAR(B11) | Q11: =TEXT(B11,"dddd")
A12: O009 | B12: 45940 | C12: South | D12: Accessories | E12: Mouse | F12: Riya | G12: 2 | H12: 900 | I12: 0.1 | J12: Completed | K12: =G12*H12 | L12: =K12*I12 | M12: =K12-L12 | N12: =M12*IF(D12="Electronics",0.15,IF(D12="Furniture",0.20,0.25)) | O12: =TEXT(B12,"mmm") | P12: =YEAR(B12) | Q12: =TEXT(B12,"dddd")
A13: O010 | B13: 45972 | C13: East | D13: Furniture | E13: Chair | F13: Rahul | G13: 3 | H13: 8500 | I13: 0 | J13: Pending | K13: =G13*H13 | L13: =K13*I13 | M13: =K13-L13 | N13: =M13*IF(D13="Electronics",0.15,IF(D13="Furniture",0.20,0.25)) | O13: =TEXT(B13,"mmm") | P13: =YEAR(B13) | Q13: =TEXT(B13,"dddd")
A14: O011 | B14: 46003 | C14: West | D14: Furniture | E14: Desk | F14: Neha | G14: 4 | H14: 12000 | I14: 0.02 | J14: Cancelled | K14: =G14*H14 | L14: =K14*I14 | M14: =K14-L14 | N14: =M14*IF(D14="Electronics",0.15,IF(D14="Furniture",0.20,0.25)) | O14: =TEXT(B14,"mmm") | P14: =YEAR(B14) | Q14: =TEXT(B14,"dddd")
A15: O012 | B15: 45670 | C15: North | D15: Accessories | E15: Keyboard | F15: Kabir | G15: 5 | H15: 1800 | I15: 0.05 | J15: Completed | K15: =G15*H15 | L15: =K15*I15 | M15: =K15-L15 | N15: =M15*IF(D15="Electronics",0.15,IF(D15="Furniture",0.20,0.25)) | O15: =TEXT(B15,"mmm") | P15: =YEAR(B15) | Q15: =TEXT(B15,"dddd")
... A83: O080 | B83: 45927 | C83: North | D83: Electronics | E83: Monitor | F83: Aarav | G83: 1 | H83: 18000 | I83: 0 | J83: Completed | K83: =G83*H83 | L83: =K83*I83 | M83: =K83-L83 | N83: =M83*IF(D83="Electronics",0.15,IF(D83="Furniture",0.20,0.25)) | O83: =TEXT(B83,"mmm") | P83: =YEAR(B83) | Q83: =TEXT(B83,"dddd")

Sheet Product_Master
A3: Product_ID | B3: Product | C3: Category | D3: Price | E3: Standard Margin
A4: P001 | B4: Laptop | C4: Electronics | D4: 55000 | E4: 0.15
A5: P002 | B5: Monitor | C5: Electronics | D5: 18000 | E5: 0.15
A6: P003 | B6: Mouse | C6: Accessories | D6: 900 | E6: 0.25
A7: P004 | B7: Chair | C7: Furniture | D7: 8500 | E7: 0.2
A8: P005 | B8: Desk | C8: Furniture | D8: 12000 | E8: 0.2
A9: P006 | B9: Keyboard | C9: Accessories | D9: 1800 | E9: 0.25

Sheet Employee_Master
A3: Employee_ID | B3: Employee | C3: Department | D3: Region | E3: Salary
A4: E001 | B4: Aarav | C4: IT | D4: South | E4: 32500
A5: E002 | B5: Riya | C5: HR | D5: East | E5: 35000
A6: E003 | B6: Rahul | C6: Finance | D6: West | E6: 37500
A7: E004 | B7: Neha | C7: Sales | D7: North | E7: 40000
A8: E005 | B8: Kabir | C8: IT | D8: South | E8: 42500
A9: E006 | B9: Sana | C9: HR | D9: East | E9: 45000
A10: E007 | B10: Ishaan | C10: Finance | D10: West | E10: 47500
A11: E008 | B11: Meera | C11: Sales | D11: North | E11: 50000

Sheet Calculations
A3: Metric | B3: Formula / Result
A4: Total Sales | B4: =SUM(Raw_Data!M4:M83)
A5: Total Profit | B5: =SUM(Raw_Data!N4:N83)
A6: Total Orders | B6: =COUNTA(Raw_Data!A4:A83)
A7: Total Quantity | B7: =SUM(Raw_Data!G4:G83)
A8: Average Order Value | B8: =B4/B6
A9: Completed Orders | B9: =COUNTIF(Raw_Data!J4:J83,"Completed")
A10: Pending Orders | B10: =COUNTIF(Raw_Data!J4:J83,"Pending")
A11: Cancelled Orders | B11: =COUNTIF(Raw_Data!J4:J83,"Cancelled")
A12: Electronics Sales | B12: =SUMIF(Raw_Data!D4:D83,"Electronics",Raw_Data!M4:M83)
A13: North Sales | B13: =SUMIF(Raw_Data!C4:C83,"North",Raw_Data!M4:M83)
A14: Completed North Sales | B14: =SUMIFS(Raw_Data!M4:M83,Raw_Data!C4:C83,"North",Raw_Data!J4:J83,"Completed")

Sheet Lookup_Text_Date
A3: Product_ID | B3: XLOOKUP Product | C3: VLOOKUP Price | D3: INDEX/MATCH Category
A4: P001 | B4: =XLOOKUP(A4,Product_Master!A:A,Product_Master!B:B,"Not Found") | C4: =IFERROR(VLOOKUP(A4,Product_Master!A:E,4,FALSE),"Not Found") | D4: =IFERROR(INDEX(Product_Master!C:C,MATCH(A4,Product_Master!A:A,0)),"Not Found")
A5: P003 | B5: =XLOOKUP(A5,Product_Master!A:A,Product_Master!B:B,"Not Found") | C5: =IFERROR(VLOOKUP(A5,Product_Master!A:E,4,FALSE),"Not Found") | D5: =IFERROR(INDEX(Product_Master!C:C,MATCH(A5,Product_Master!A:A,0)),"Not Found")
A6: P006 | B6: =XLOOKUP(A6,Product_Master!A:A,Product_Master!B:B,"Not Found") | C6: =IFERROR(VLOOKUP(A6,Product_Master!A:E,4,FALSE),"Not Found") | D6: =IFERROR(INDEX(Product_Master!C:C,MATCH(A6,Product_Master!A:A,0)),"Not Found")
A7: P999 | B7: =XLOOKUP(A7,Product_Master!A:A,Product_Master!B:B,"Not Found") | C7: =IFERROR(VLOOKUP(A7,Product_Master!A:E,4,FALSE),"Not Found") | D7: =IFERROR(INDEX(Product_Master!C:C,MATCH(A7,Product_Master!A:A,0)),"Not Found")
A10: Function | B10: Formula
A11: CONCAT | B11: =CONCAT("Excel"," ","Project")
A12: TEXTJOIN | B12: =TEXTJOIN(" - ",TRUE,"Excel","SQL","Python")
A13: SUBSTITUTE | B13: =SUBSTITUTE("Sales Analysis","Sales","Data")
A14: FIND | B14: =FIND("@","test@example.com")
A15: YEAR | B15: =YEAR(TODAY())
A16: MONTH | B16: =MONTH(TODAY())
A17: DAY | B17: =DAY(TODAY())
A18: EOMONTH | B18: =EOMONTH(TODAY(),0)

Sheet Pivot_Analysis
A3: Region | B3: Sales | C3: Profit | D3: Orders | E3: Profit Margin
A4: North | B4: =SUMIF(Raw_Data!C4:C83,A4,Raw_Data!M4:M83) | C4: =SUMIF(Raw_Data!C4:C83,A4,Raw_Data!N4:N83) | D4: =COUNTIF(Raw_Data!C4:C83,A4) | E4: =C4/B4
A5: South | B5: =SUMIF(Raw_Data!C4:C83,A5,Raw_Data!M4:M83) | C5: =SUMIF(Raw_Data!C4:C83,A5,Raw_Data!N4:N83) | D5: =COUNTIF(Raw_Data!C4:C83,A5) | E5: =C5/B5
A6: East | B6: =SUMIF(Raw_Data!C4:C83,A6,Raw_Data!M4:M83) | C6: =SUMIF(Raw_Data!C4:C83,A6,Raw_Data!N4:N83) | D6: =COUNTIF(Raw_Data!C4:C83,A6) | E6: =C6/B6
A7: West | B7: =SUMIF(Raw_Data!C4:C83,A7,Raw_Data!M4:M83) | C7: =SUMIF(Raw_Data!C4:C83,A7,Raw_Data!N4:N83) | D7: =COUNTIF(Raw_Data!C4:C83,A7) | E7: =C7/B7
A10: Category | B10: Sales | C10: Orders
A11: Electronics | B11: =SUMIF(Raw_Data!D4:D83,A11,Raw_Data!M4:M83) | C11: =COUNTIF(Raw_Data!D4:D83,A11)
A12: Furniture | B12: =SUMIF(Raw_Data!D4:D83,A12,Raw_Data!M4:M83) | C12: =COUNTIF(Raw_Data!D4:D83,A12)
A13: Accessories | B13: =SUMIF(Raw_Data!D4:D83,A13,Raw_Data!M4:M83) | C13: =COUNTIF(Raw_Data!D4:D83,A13)

Sheet Dashboard
A1: FINAL SALES ANALYTICS DASHBOARD
A4: Total Sales =Calculations!B4 | D4: Total Profit =Calculations!B5 | G4: Orders =Calculations!B6 | J4: Avg Order =Calculations!B8
A9: Region | B9: Sales | C9: Profit | D9: Orders
A10: =Pivot_Analysis!A4 | B10: =Pivot_Analysis!B4 | C10: =Pivot_Analysis!C4 | D10: =Pivot_Analysis!D4
A11: =Pivot_Analysis!A5 | B11: =Pivot_Analysis!B5 | C11: =Pivot_Analysis!C5 | D11: =Pivot_Analysis!D5
A12: =Pivot_Analysis!A6 | B12: =Pivot_Analysis!B6 | C12: =Pivot_Analysis!C6 | D12: =Pivot_Analysis!D6
A13: =Pivot_Analysis!A7 | B13: =Pivot_Analysis!B7 | C13: =Pivot_Analysis!C7 | D13: =Pivot_Analysis!D7
